anysnake/__init__.py
anysnake/snake.py
anysnake-0.2.0.dist-info/METADATA
anysnake-0.2.0.dist-info/WHEEL
anysnake-0.2.0.dist-info/licenses/LICENSE
anysnake-0.2.0.dist-info/RECORD
