Metadata-Version: 2.4
Name: anysnake
Version: 0.2.0
Summary: A python library to allow you to play snake on anything!
Project-URL: Homepage, https://github.com/Jamackey/anysnake
Project-URL: Issues, https://github.com/Jamackey/anysnake/issues
Author: James Mackey
License: MIT
License-File: LICENSE
Requires-Python: >=3.8
Requires-Dist: numpy
Requires-Dist: pynput
